aws_scraper/__init__.py
aws_scraper/__main__.py
aws_scraper/aws.py
aws_scraper/io.py
aws_scraper/scrape.py
aws_scraper/utils.py
aws_scraper-0.1.4.dist-info/entry_points.txt
aws_scraper-0.1.4.dist-info/WHEEL
aws_scraper-0.1.4.dist-info/METADATA
aws_scraper-0.1.4.dist-info/RECORD
