Metadata-Version: 2.1
Name: aws-scraper
Version: 0.1.4
Summary: A Python utility for submitting and running scraping jobs in parallel on AWS ECS Fargate.
Author: Nick Hand
Author-email: nick.hand@phila.gov
Requires-Python: >=3.8,<4.0
Classifier: Programming Language :: Python :: 3
Classifier: Programming Language :: Python :: 3.10
Classifier: Programming Language :: Python :: 3.8
Classifier: Programming Language :: Python :: 3.9
Requires-Dist: aiobotocore (>=2.1.0,<3.0.0)
Requires-Dist: boto3 (<2)
Requires-Dist: loguru (>=0.5.3,<0.6.0)
Requires-Dist: pandas (>=1.4.1,<2.0.0)
Requires-Dist: python-dotenv (>=0.19.2,<0.20.0)
Requires-Dist: s3fs (>=2022.1.0,<2023.0.0)
Requires-Dist: selenium (>=4.1.3,<5.0.0)
Requires-Dist: selenium-stealth (>=1.0.6,<2.0.0)
Requires-Dist: simplejson (>=3.17.6,<4.0.0)
Requires-Dist: tryagain (>=1.0,<2.0)
Requires-Dist: webdriver-manager (>=3.5.3,<4.0.0)
